awsvault/__init__.py
awsvault/core.py
awsvault-0.1.1.dist-info/DESCRIPTION.rst
awsvault-0.1.1.dist-info/METADATA
awsvault-0.1.1.dist-info/RECORD
awsvault-0.1.1.dist-info/WHEEL
awsvault-0.1.1.dist-info/metadata.json
awsvault-0.1.1.dist-info/top_level.txt
