Metadata-Version: 2.0
Name: awsvault
Version: 0.1.1
Summary: AWS secrets manager helper
Home-page: https://github.com/spacetimelabs/awsvault
Author: Spacetime Labs
Author-email: dev@spacetimelabs.ai
License: BSD
Download-URL: https://github.com/spacetimelabs/awsvault/tarball/0.1.1
Keywords: AWS Secrets Manager
Platform: UNKNOWN
Classifier: Development Status :: 3 - Alpha
Classifier: Intended Audience :: Developers
Classifier: Programming Language :: Python :: 3
Requires-Dist: boto3 (<2.0.0,>=1.9.0)
